simple/__init__.py
simple_core-0.0.0.dist-info/LICENSE
simple_core-0.0.0.dist-info/METADATA
simple_core-0.0.0.dist-info/WHEEL
simple_core-0.0.0.dist-info/top_level.txt
simple_core-0.0.0.dist-info/RECORD
